{"name":"PlaceholderAPIPlugin","comment":"Yes I have a shit load of work to do...","isClass":true,"isInterface":false,"isEnum":false,"isEnumConstant":false,"isConstructor":false,"isField":false,"isMethod":false,"isOrdinaryClass":true,"isPrimitive":false,"simpleName":"PlaceholderAPIPlugin","qualifiedName":"me.clip.placeholderapi.PlaceholderAPIPlugin","dimension":"","elementType":{},"package":"me.clip.placeholderapi","superclass":"org.bukkit.plugin.java.JavaPlugin","interfaces":[],"isAbstract":false,"isStatic":false,"innerClasses":[],"isInnerClass":false,"constructors":[{"name":"PlaceholderAPIPlugin","comment":"","isClass":false,"isInterface":false,"isEnum":false,"isEnumConstant":false,"isConstructor":true,"isField":false,"isMethod":false,"isOrdinaryClass":false,"signature":"()","flatSignature":"()","parameters":[],"typeParameters":[]}],"fields":[],"methods":[{"name":"getInstance","comment":"Gets the static instance of the main class for PlaceholderAPI. This class is not the actual API\n class, this is the main class that extends JavaPlugin. For most API methods, use static methods\n available from the class: {@link PlaceholderAPI}","isClass":false,"isInterface":false,"isEnum":false,"isEnumConstant":false,"isConstructor":false,"isField":false,"isMethod":true,"isOrdinaryClass":false,"signature":"()","flatSignature":"()","returnType":{"isPrimitive":false,"simpleName":"PlaceholderAPIPlugin","qualifiedName":"me.clip.placeholderapi.PlaceholderAPIPlugin","dimension":"","elementType":{}},"isAbstract":false,"isDefault":false,"isStatic":true,"parameters":[],"typeParameters":[]},{"name":"getDateFormat","comment":"Get the configurable {@linkplain SimpleDateFormat} object that is used to parse time for\n generic time based placeholders","isClass":false,"isInterface":false,"isEnum":false,"isEnumConstant":false,"isConstructor":false,"isField":false,"isMethod":true,"isOrdinaryClass":false,"signature":"()","flatSignature":"()","returnType":{"isPrimitive":false,"simpleName":"SimpleDateFormat","qualifiedName":"java.text.SimpleDateFormat","dimension":"","elementType":{}},"isAbstract":false,"isDefault":false,"isStatic":true,"parameters":[],"typeParameters":[]},{"name":"booleanTrue","comment":"Get the configurable {@linkplain String} value that should be returned when a boolean is true","isClass":false,"isInterface":false,"isEnum":false,"isEnumConstant":false,"isConstructor":false,"isField":false,"isMethod":true,"isOrdinaryClass":false,"signature":"()","flatSignature":"()","returnType":{"isPrimitive":false,"simpleName":"String","qualifiedName":"java.lang.String","dimension":"","elementType":{}},"isAbstract":false,"isDefault":false,"isStatic":true,"parameters":[],"typeParameters":[]},{"name":"booleanFalse","comment":"Get the configurable {@linkplain String} value that should be returned when a boolean is false","isClass":false,"isInterface":false,"isEnum":false,"isEnumConstant":false,"isConstructor":false,"isField":false,"isMethod":true,"isOrdinaryClass":false,"signature":"()","flatSignature":"()","returnType":{"isPrimitive":false,"simpleName":"String","qualifiedName":"java.lang.String","dimension":"","elementType":{}},"isAbstract":false,"isDefault":false,"isStatic":true,"parameters":[],"typeParameters":[]},{"name":"getServerVersion","comment":"","isClass":false,"isInterface":false,"isEnum":false,"isEnumConstant":false,"isConstructor":false,"isField":false,"isMethod":true,"isOrdinaryClass":false,"signature":"()","flatSignature":"()","returnType":{"isPrimitive":false,"simpleName":"Version","qualifiedName":"me.clip.placeholderapi.expansion.Version","dimension":"","elementType":{}},"isAbstract":false,"isDefault":false,"isStatic":true,"parameters":[],"typeParameters":[]},{"name":"onLoad","comment":"","isClass":false,"isInterface":false,"isEnum":false,"isEnumConstant":false,"isConstructor":false,"isField":false,"isMethod":true,"isOrdinaryClass":false,"signature":"()","flatSignature":"()","returnType":{"isPrimitive":true,"simpleName":"void","qualifiedName":"void","dimension":"","elementType":{}},"isAbstract":false,"isDefault":false,"isStatic":false,"parameters":[],"typeParameters":[]},{"name":"onEnable","comment":"","isClass":false,"isInterface":false,"isEnum":false,"isEnumConstant":false,"isConstructor":false,"isField":false,"isMethod":true,"isOrdinaryClass":false,"signature":"()","flatSignature":"()","returnType":{"isPrimitive":true,"simpleName":"void","qualifiedName":"void","dimension":"","elementType":{}},"isAbstract":false,"isDefault":false,"isStatic":false,"parameters":[],"typeParameters":[]},{"name":"onDisable","comment":"","isClass":false,"isInterface":false,"isEnum":false,"isEnumConstant":false,"isConstructor":false,"isField":false,"isMethod":true,"isOrdinaryClass":false,"signature":"()","flatSignature":"()","returnType":{"isPrimitive":true,"simpleName":"void","qualifiedName":"void","dimension":"","elementType":{}},"isAbstract":false,"isDefault":false,"isStatic":false,"parameters":[],"typeParameters":[]},{"name":"reloadConf","comment":"","isClass":false,"isInterface":false,"isEnum":false,"isEnumConstant":false,"isConstructor":false,"isField":false,"isMethod":true,"isOrdinaryClass":false,"signature":"(org.bukkit.command.CommandSender)","flatSignature":"(CommandSender)","returnType":{"isPrimitive":true,"simpleName":"void","qualifiedName":"void","dimension":"","elementType":{}},"isAbstract":false,"isDefault":false,"isStatic":false,"parameters":[{"name":"s","type":{"isPrimitive":false,"simpleName":"CommandSender","qualifiedName":"org.bukkit.command.CommandSender","dimension":"","elementType":{}}}],"typeParameters":[]},{"name":"enableCloud","comment":"","isClass":false,"isInterface":false,"isEnum":false,"isEnumConstant":false,"isConstructor":false,"isField":false,"isMethod":true,"isOrdinaryClass":false,"signature":"()","flatSignature":"()","returnType":{"isPrimitive":true,"simpleName":"void","qualifiedName":"void","dimension":"","elementType":{}},"isAbstract":false,"isDefault":false,"isStatic":false,"parameters":[],"typeParameters":[]},{"name":"disableCloud","comment":"","isClass":false,"isInterface":false,"isEnum":false,"isEnumConstant":false,"isConstructor":false,"isField":false,"isMethod":true,"isOrdinaryClass":false,"signature":"()","flatSignature":"()","returnType":{"isPrimitive":true,"simpleName":"void","qualifiedName":"void","dimension":"","elementType":{}},"isAbstract":false,"isDefault":false,"isStatic":false,"parameters":[],"typeParameters":[]},{"name":"getPlaceholderAPIConfig","comment":"Obtain the configuration class for PlaceholderAPI.","isClass":false,"isInterface":false,"isEnum":false,"isEnumConstant":false,"isConstructor":false,"isField":false,"isMethod":true,"isOrdinaryClass":false,"signature":"()","flatSignature":"()","returnType":{"isPrimitive":false,"simpleName":"PlaceholderAPIConfig","qualifiedName":"me.clip.placeholderapi.configuration.PlaceholderAPIConfig","dimension":"","elementType":{}},"isAbstract":false,"isDefault":false,"isStatic":false,"parameters":[],"typeParameters":[]},{"name":"getExpansionManager","comment":"","isClass":false,"isInterface":false,"isEnum":false,"isEnumConstant":false,"isConstructor":false,"isField":false,"isMethod":true,"isOrdinaryClass":false,"signature":"()","flatSignature":"()","returnType":{"isPrimitive":false,"simpleName":"ExpansionManager","qualifiedName":"me.clip.placeholderapi.expansion.ExpansionManager","dimension":"","elementType":{}},"isAbstract":false,"isDefault":false,"isStatic":false,"parameters":[],"typeParameters":[]},{"name":"getExpansionCloud","comment":"","isClass":false,"isInterface":false,"isEnum":false,"isEnumConstant":false,"isConstructor":false,"isField":false,"isMethod":true,"isOrdinaryClass":false,"signature":"()","flatSignature":"()","returnType":{"isPrimitive":false,"simpleName":"ExpansionCloudManager","qualifiedName":"me.clip.placeholderapi.expansion.cloud.ExpansionCloudManager","dimension":"","elementType":{}},"isAbstract":false,"isDefault":false,"isStatic":false,"parameters":[],"typeParameters":[]},{"name":"getUptime","comment":"","isClass":false,"isInterface":false,"isEnum":false,"isEnumConstant":false,"isConstructor":false,"isField":false,"isMethod":true,"isOrdinaryClass":false,"signature":"()","flatSignature":"()","returnType":{"isPrimitive":false,"simpleName":"String","qualifiedName":"java.lang.String","dimension":"","elementType":{}},"isAbstract":false,"isDefault":false,"isStatic":false,"parameters":[],"typeParameters":[]},{"name":"getUptimeMillis","comment":"","isClass":false,"isInterface":false,"isEnum":false,"isEnumConstant":false,"isConstructor":false,"isField":false,"isMethod":true,"isOrdinaryClass":false,"signature":"()","flatSignature":"()","returnType":{"isPrimitive":true,"simpleName":"long","qualifiedName":"long","dimension":"","elementType":{}},"isAbstract":false,"isDefault":false,"isStatic":false,"parameters":[],"typeParameters":[]}],"typeParameters":[],"enumConstants":[]}