{"name":"FileUtil","isClass":true,"isInterface":false,"isEnum":false,"isEnumConstant":false,"isConstructor":false,"isField":false,"isMethod":false,"isOrdinaryClass":true,"isPrimitive":false,"simpleName":"FileUtil","qualifiedName":"me.clip.placeholderapi.util.FileUtil","dimension":"","elementType":{},"package":"me.clip.placeholderapi.util","superclass":"java.lang.Object","interfaces":[],"isAbstract":false,"isStatic":false,"innerClasses":[],"isInnerClass":false,"constructors":[{"name":"FileUtil","isClass":false,"isInterface":false,"isEnum":false,"isEnumConstant":false,"isConstructor":true,"isField":false,"isMethod":false,"isOrdinaryClass":false,"signature":"()","flatSignature":"()","parameters":[],"typeParameters":[]}],"fields":[],"methods":[{"name":"getClasses","isClass":false,"isInterface":false,"isEnum":false,"isEnumConstant":false,"isConstructor":false,"isField":false,"isMethod":true,"isOrdinaryClass":false,"signature":"(java.lang.String, java.lang.Class\u003c?\u003e)","flatSignature":"(String, Class\u003c?\u003e)","returnType":{"isPrimitive":false,"simpleName":"List","qualifiedName":"java.util.List","dimension":"","elementType":{}},"isAbstract":false,"isDefault":false,"isStatic":true,"parameters":[{"name":"folder","type":{"isPrimitive":false,"simpleName":"String","qualifiedName":"java.lang.String","dimension":"","elementType":{}}},{"name":"type","type":{"isPrimitive":false,"simpleName":"Class","qualifiedName":"java.lang.Class","dimension":"","elementType":{}}}],"typeParameters":[]},{"name":"getClasses","isClass":false,"isInterface":false,"isEnum":false,"isEnumConstant":false,"isConstructor":false,"isField":false,"isMethod":true,"isOrdinaryClass":false,"signature":"(java.lang.String, java.lang.String, java.lang.Class\u003c?\u003e)","flatSignature":"(String, String, Class\u003c?\u003e)","returnType":{"isPrimitive":false,"simpleName":"List","qualifiedName":"java.util.List","dimension":"","elementType":{}},"isAbstract":false,"isDefault":false,"isStatic":true,"parameters":[{"name":"folder","type":{"isPrimitive":false,"simpleName":"String","qualifiedName":"java.lang.String","dimension":"","elementType":{}}},{"name":"fileName","type":{"isPrimitive":false,"simpleName":"String","qualifiedName":"java.lang.String","dimension":"","elementType":{}}},{"name":"type","type":{"isPrimitive":false,"simpleName":"Class","qualifiedName":"java.lang.Class","dimension":"","elementType":{}}}],"typeParameters":[]}],"typeParameters":[],"enumConstants":[]}